startorch/__init__.py
startorch/constants.py
startorch/example/__init__.py
startorch/example/base.py
startorch/example/blobs.py
startorch/example/cache.py
startorch/example/circles.py
startorch/example/concatenate.py
startorch/example/friedman.py
startorch/example/hypercube.py
startorch/example/moons.py
startorch/example/regression.py
startorch/example/sparse_uncorrelated.py
startorch/example/swissroll.py
startorch/example/tensor.py
startorch/example/timeseries.py
startorch/example/transform.py
startorch/example/vanilla.py
startorch/integration/__init__.py
startorch/integration/iden/__init__.py
startorch/integration/iden/data/__init__.py
startorch/integration/iden/data/generator/__init__.py
startorch/integration/iden/data/generator/example.py
startorch/periodic/__init__.py
startorch/periodic/sequence/__init__.py
startorch/periodic/sequence/base.py
startorch/periodic/sequence/repeat.py
startorch/periodic/sequence/wave.py
startorch/periodic/timeseries/__init__.py
startorch/periodic/timeseries/base.py
startorch/periodic/timeseries/repeat.py
startorch/plot/__init__.py
startorch/plot/matplotlib/__init__.py
startorch/plot/matplotlib/feature.py
startorch/plot/matplotlib/sequence.py
startorch/plot/plotly/__init__.py
startorch/plot/plotly/feature.py
startorch/plot/plotly/sequence.py
startorch/random/__init__.py
startorch/random/bounded.py
startorch/random/discrete.py
startorch/random/infinite.py
startorch/random/semi_infinite.py
startorch/sequence/__init__.py
startorch/sequence/ar.py
startorch/sequence/base.py
startorch/sequence/categorical.py
startorch/sequence/cauchy.py
startorch/sequence/choice.py
startorch/sequence/constant.py
startorch/sequence/dtype.py
startorch/sequence/exponential.py
startorch/sequence/halfcauchy.py
startorch/sequence/halfnormal.py
startorch/sequence/joining.py
startorch/sequence/linear.py
startorch/sequence/lognormal.py
startorch/sequence/markov.py
startorch/sequence/math.py
startorch/sequence/normal.py
startorch/sequence/periodic.py
startorch-0.2.0.dist-info/LICENSE
startorch-0.2.0.dist-info/METADATA
startorch-0.2.0.dist-info/WHEEL
startorch-0.2.0.dist-info/RECORD
