Metadata-Version: 2.1
Name: startorch
Version: 0.2.0
Summary: synthetic time-series generator in PyTorch
Home-page: https://github.com/durandtibo/startorch
License: BSD-3-Clause
Keywords: synthetic,time-series,pytorch
Author: Thibaut Durand
Author-email: durand.tibo+gh@gmail.com
Requires-Python: >=3.9,<3.13
Classifier: Development Status :: 4 - Beta
Classifier: Intended Audience :: Developers
Classifier: Intended Audience :: Information Technology
Classifier: Intended Audience :: Science/Research
Classifier: License :: OSI Approved :: BSD License
Classifier: Operating System :: POSIX :: Linux
Classifier: Programming Language :: Python :: 3
Classifier: Programming Language :: Python :: 3.9
Classifier: Programming Language :: Python :: 3.10
Classifier: Programming Language :: Python :: 3.11
Classifier: Programming Language :: Python :: 3.12
Classifier: Topic :: Scientific/Engineering
Classifier: Topic :: Software Development :: Libraries
Provides-Extra: all
Requires-Dist: batchtensor (>=0.0.2,<0.1)
Requires-Dist: coola (>=0.2,<1.0)
Requires-Dist: iden (>=0.0.2,<0.1) ; extra == "all"
Requires-Dist: matplotlib (>=3.6,<4.0) ; extra == "all"
Requires-Dist: numpy (>=1.23,<2.0)
Requires-Dist: objectory (>=0.1,<1.0)
Requires-Dist: plotly (>=5.0,<6.0) ; extra == "all"
Requires-Dist: torch (>=2.0,<2.3) ; sys_platform == "darwin" and platform_machine != "arm64"
Requires-Dist: torch (>=2.0,<3.0)
Project-URL: Repository, https://github.com/durandtibo/startorch
